ready_logger/__init__.py
ready_logger/ready_logger.py
ready_logger-1.0.0.dist-info/WHEEL
ready_logger-1.0.0.dist-info/METADATA
ready_logger-1.0.0.dist-info/RECORD
