Metadata-Version: 2.1
Name: ready-logger
Version: 1.0.0
Summary: Easily configure Python loggers.
Home-page: https://github.com/djkelleher/ready-logger
License: MIT
Keywords: logs,logger,loggers,logging
Author: Dan Kelleher
Author-email: kelleherjdan@gmail.com
Requires-Python: >=3.7
Classifier: License :: OSI Approved :: MIT License
Classifier: Programming Language :: Python
Classifier: Programming Language :: Python :: 3
Classifier: Programming Language :: Python :: 3.7
Classifier: Programming Language :: Python :: 3.8
Classifier: Programming Language :: Python :: 3.9
Classifier: Programming Language :: Python :: 3.10
Classifier: Programming Language :: Python :: 3.11
Classifier: Programming Language :: Python :: 3
Classifier: Topic :: Software Development
Classifier: Topic :: Software Development :: Libraries
Classifier: Topic :: Software Development :: Libraries :: Python Modules
Classifier: Topic :: System :: Logging
Project-URL: Repository, https://github.com/djkelleher/ready-logger
